visa/__init__.py
visa/api_requestor.py
visa/error.py
visa/http_client.py
visa/multipart_data_generator.py
visa/oauth.py
visa/oauth_error.py
visa/request_metrics.py
visa/six.py
visa/util.py
visa/version.py
visa/visa_response.py
visa-1.0.0.dist-info/LICENSE
visa-1.0.0.dist-info/METADATA
visa-1.0.0.dist-info/WHEEL
visa-1.0.0.dist-info/top_level.txt
visa-1.0.0.dist-info/RECORD
