Metadata-Version: 1.2
Name: visa
Version: 1.0.0
Summary: Python bindings for the VISA API
Home-page: https://github.com/visa-sdk/visa-python
Author: VISA
Author-email: hprobotic@gmail.com
License: MIT
Project-URL: Bug Tracker, https://github.com/visa-sdk/visa-python/issues
Project-URL: Documentation, https://visa.com/docs/api/python
Project-URL: Source Code, https://github.com/visa-sdk/visa-python
Keywords: visa api payments
Platform: UNKNOWN
Classifier: Development Status :: 5 - Production/Stable
Classifier: Intended Audience :: Developers
Classifier: License :: OSI Approved :: MIT License
Classifier: Operating System :: OS Independent
Classifier: Programming Language :: Python
Classifier: Programming Language :: Python :: 2
Classifier: Programming Language :: Python :: 2.7
Classifier: Programming Language :: Python :: 3
Classifier: Programming Language :: Python :: 3.4
Classifier: Programming Language :: Python :: 3.5
Classifier: Programming Language :: Python :: 3.6
Classifier: Programming Language :: Python :: 3.7
Classifier: Programming Language :: Python :: Implementation :: PyPy
Classifier: Topic :: Software Development :: Libraries :: Python Modules
Requires-Python: >=2.7, !=3.0.*, !=3.1.*, !=3.2.*, !=3.3.*
